{ "frames": {
   "background-explosion-animated 0.aseprite": {
    "frame": { "x": 0, "y": 0, "w": 100, "h": 100 },
    "rotated": false,
    "trimmed": false,
    "spriteSourceSize": { "x": 0, "y": 0, "w": 100, "h": 100 },
    "sourceSize": { "w": 100, "h": 100 },
    "duration": 100
   },
   "background-explosion-animated 1.aseprite": {
    "frame": { "x": 100, "y": 0, "w": 100, "h": 100 },
    "rotated": false,
    "trimmed": false,
    "spriteSourceSize": { "x": 0, "y": 0, "w": 100, "h": 100 },
    "sourceSize": { "w": 100, "h": 100 },
    "duration": 100
   },
   "background-explosion-animated 2.aseprite": {
    "frame": { "x": 200, "y": 0, "w": 100, "h": 100 },
    "rotated": false,
    "trimmed": false,
    "spriteSourceSize": { "x": 0, "y": 0, "w": 100, "h": 100 },
    "sourceSize": { "w": 100, "h": 100 },
    "duration": 100
   },
   "background-explosion-animated 3.aseprite": {
    "frame": { "x": 300, "y": 0, "w": 100, "h": 100 },
    "rotated": false,
    "trimmed": false,
    "spriteSourceSize": { "x": 0, "y": 0, "w": 100, "h": 100 },
    "sourceSize": { "w": 100, "h": 100 },
    "duration": 100
   },
   "background-explosion-animated 4.aseprite": {
    "frame": { "x": 400, "y": 0, "w": 100, "h": 100 },
    "rotated": false,
    "trimmed": false,
    "spriteSourceSize": { "x": 0, "y": 0, "w": 100, "h": 100 },
    "sourceSize": { "w": 100, "h": 100 },
    "duration": 100
   },
   "background-explosion-animated 5.aseprite": {
    "frame": { "x": 500, "y": 0, "w": 100, "h": 100 },
    "rotated": false,
    "trimmed": false,
    "spriteSourceSize": { "x": 0, "y": 0, "w": 100, "h": 100 },
    "sourceSize": { "w": 100, "h": 100 },
    "duration": 100
   },
   "background-explosion-animated 6.aseprite": {
    "frame": { "x": 600, "y": 0, "w": 100, "h": 100 },
    "rotated": false,
    "trimmed": false,
    "spriteSourceSize": { "x": 0, "y": 0, "w": 100, "h": 100 },
    "sourceSize": { "w": 100, "h": 100 },
    "duration": 100
   },
   "background-explosion-animated 7.aseprite": {
    "frame": { "x": 700, "y": 0, "w": 100, "h": 100 },
    "rotated": false,
    "trimmed": false,
    "spriteSourceSize": { "x": 0, "y": 0, "w": 100, "h": 100 },
    "sourceSize": { "w": 100, "h": 100 },
    "duration": 100
   },
   "background-explosion-animated 8.aseprite": {
    "frame": { "x": 800, "y": 0, "w": 100, "h": 100 },
    "rotated": false,
    "trimmed": false,
    "spriteSourceSize": { "x": 0, "y": 0, "w": 100, "h": 100 },
    "sourceSize": { "w": 100, "h": 100 },
    "duration": 100
   },
   "background-explosion-animated 9.aseprite": {
    "frame": { "x": 900, "y": 0, "w": 100, "h": 100 },
    "rotated": false,
    "trimmed": false,
    "spriteSourceSize": { "x": 0, "y": 0, "w": 100, "h": 100 },
    "sourceSize": { "w": 100, "h": 100 },
    "duration": 100
   },
   "background-explosion-animated 10.aseprite": {
    "frame": { "x": 1000, "y": 0, "w": 100, "h": 100 },
    "rotated": false,
    "trimmed": false,
    "spriteSourceSize": { "x": 0, "y": 0, "w": 100, "h": 100 },
    "sourceSize": { "w": 100, "h": 100 },
    "duration": 100
   },
   "background-explosion-animated 11.aseprite": {
    "frame": { "x": 1100, "y": 0, "w": 100, "h": 100 },
    "rotated": false,
    "trimmed": false,
    "spriteSourceSize": { "x": 0, "y": 0, "w": 100, "h": 100 },
    "sourceSize": { "w": 100, "h": 100 },
    "duration": 100
   },
   "background-explosion-animated 12.aseprite": {
    "frame": { "x": 1200, "y": 0, "w": 100, "h": 100 },
    "rotated": false,
    "trimmed": false,
    "spriteSourceSize": { "x": 0, "y": 0, "w": 100, "h": 100 },
    "sourceSize": { "w": 100, "h": 100 },
    "duration": 100
   },
   "background-explosion-animated 13.aseprite": {
    "frame": { "x": 1300, "y": 0, "w": 100, "h": 100 },
    "rotated": false,
    "trimmed": false,
    "spriteSourceSize": { "x": 0, "y": 0, "w": 100, "h": 100 },
    "sourceSize": { "w": 100, "h": 100 },
    "duration": 100
   },
   "background-explosion-animated 14.aseprite": {
    "frame": { "x": 1400, "y": 0, "w": 100, "h": 100 },
    "rotated": false,
    "trimmed": false,
    "spriteSourceSize": { "x": 0, "y": 0, "w": 100, "h": 100 },
    "sourceSize": { "w": 100, "h": 100 },
    "duration": 100
   },
   "background-explosion-animated 15.aseprite": {
    "frame": { "x": 1500, "y": 0, "w": 100, "h": 100 },
    "rotated": false,
    "trimmed": false,
    "spriteSourceSize": { "x": 0, "y": 0, "w": 100, "h": 100 },
    "sourceSize": { "w": 100, "h": 100 },
    "duration": 100
   },
   "background-explosion-animated 16.aseprite": {
    "frame": { "x": 1600, "y": 0, "w": 100, "h": 100 },
    "rotated": false,
    "trimmed": false,
    "spriteSourceSize": { "x": 0, "y": 0, "w": 100, "h": 100 },
    "sourceSize": { "w": 100, "h": 100 },
    "duration": 100
   },
   "background-explosion-animated 17.aseprite": {
    "frame": { "x": 1700, "y": 0, "w": 100, "h": 100 },
    "rotated": false,
    "trimmed": false,
    "spriteSourceSize": { "x": 0, "y": 0, "w": 100, "h": 100 },
    "sourceSize": { "w": 100, "h": 100 },
    "duration": 100
   },
   "background-explosion-animated 18.aseprite": {
    "frame": { "x": 1800, "y": 0, "w": 100, "h": 100 },
    "rotated": false,
    "trimmed": false,
    "spriteSourceSize": { "x": 0, "y": 0, "w": 100, "h": 100 },
    "sourceSize": { "w": 100, "h": 100 },
    "duration": 100
   },
   "background-explosion-animated 19.aseprite": {
    "frame": { "x": 1900, "y": 0, "w": 100, "h": 100 },
    "rotated": false,
    "trimmed": false,
    "spriteSourceSize": { "x": 0, "y": 0, "w": 100, "h": 100 },
    "sourceSize": { "w": 100, "h": 100 },
    "duration": 100
   },
   "background-explosion-animated 20.aseprite": {
    "frame": { "x": 2000, "y": 0, "w": 100, "h": 100 },
    "rotated": false,
    "trimmed": false,
    "spriteSourceSize": { "x": 0, "y": 0, "w": 100, "h": 100 },
    "sourceSize": { "w": 100, "h": 100 },
    "duration": 100
   },
   "background-explosion-animated 21.aseprite": {
    "frame": { "x": 2100, "y": 0, "w": 100, "h": 100 },
    "rotated": false,
    "trimmed": false,
    "spriteSourceSize": { "x": 0, "y": 0, "w": 100, "h": 100 },
    "sourceSize": { "w": 100, "h": 100 },
    "duration": 100
   },
   "background-explosion-animated 22.aseprite": {
    "frame": { "x": 2200, "y": 0, "w": 100, "h": 100 },
    "rotated": false,
    "trimmed": false,
    "spriteSourceSize": { "x": 0, "y": 0, "w": 100, "h": 100 },
    "sourceSize": { "w": 100, "h": 100 },
    "duration": 100
   },
   "background-explosion-animated 23.aseprite": {
    "frame": { "x": 2300, "y": 0, "w": 100, "h": 100 },
    "rotated": false,
    "trimmed": false,
    "spriteSourceSize": { "x": 0, "y": 0, "w": 100, "h": 100 },
    "sourceSize": { "w": 100, "h": 100 },
    "duration": 100
   },
   "background-explosion-animated 24.aseprite": {
    "frame": { "x": 2400, "y": 0, "w": 100, "h": 100 },
    "rotated": false,
    "trimmed": false,
    "spriteSourceSize": { "x": 0, "y": 0, "w": 100, "h": 100 },
    "sourceSize": { "w": 100, "h": 100 },
    "duration": 100
   },
   "background-explosion-animated 25.aseprite": {
    "frame": { "x": 2500, "y": 0, "w": 100, "h": 100 },
    "rotated": false,
    "trimmed": false,
    "spriteSourceSize": { "x": 0, "y": 0, "w": 100, "h": 100 },
    "sourceSize": { "w": 100, "h": 100 },
    "duration": 100
   },
   "background-explosion-animated 26.aseprite": {
    "frame": { "x": 2600, "y": 0, "w": 100, "h": 100 },
    "rotated": false,
    "trimmed": false,
    "spriteSourceSize": { "x": 0, "y": 0, "w": 100, "h": 100 },
    "sourceSize": { "w": 100, "h": 100 },
    "duration": 100
   },
   "background-explosion-animated 27.aseprite": {
    "frame": { "x": 2700, "y": 0, "w": 100, "h": 100 },
    "rotated": false,
    "trimmed": false,
    "spriteSourceSize": { "x": 0, "y": 0, "w": 100, "h": 100 },
    "sourceSize": { "w": 100, "h": 100 },
    "duration": 100
   },
   "background-explosion-animated 28.aseprite": {
    "frame": { "x": 2800, "y": 0, "w": 100, "h": 100 },
    "rotated": false,
    "trimmed": false,
    "spriteSourceSize": { "x": 0, "y": 0, "w": 100, "h": 100 },
    "sourceSize": { "w": 100, "h": 100 },
    "duration": 100
   },
   "background-explosion-animated 29.aseprite": {
    "frame": { "x": 2900, "y": 0, "w": 100, "h": 100 },
    "rotated": false,
    "trimmed": false,
    "spriteSourceSize": { "x": 0, "y": 0, "w": 100, "h": 100 },
    "sourceSize": { "w": 100, "h": 100 },
    "duration": 100
   },
   "background-explosion-animated 30.aseprite": {
    "frame": { "x": 3000, "y": 0, "w": 100, "h": 100 },
    "rotated": false,
    "trimmed": false,
    "spriteSourceSize": { "x": 0, "y": 0, "w": 100, "h": 100 },
    "sourceSize": { "w": 100, "h": 100 },
    "duration": 100
   },
   "background-explosion-animated 31.aseprite": {
    "frame": { "x": 3100, "y": 0, "w": 100, "h": 100 },
    "rotated": false,
    "trimmed": false,
    "spriteSourceSize": { "x": 0, "y": 0, "w": 100, "h": 100 },
    "sourceSize": { "w": 100, "h": 100 },
    "duration": 100
   },
   "background-explosion-animated 32.aseprite": {
    "frame": { "x": 3200, "y": 0, "w": 100, "h": 100 },
    "rotated": false,
    "trimmed": false,
    "spriteSourceSize": { "x": 0, "y": 0, "w": 100, "h": 100 },
    "sourceSize": { "w": 100, "h": 100 },
    "duration": 100
   },
   "background-explosion-animated 33.aseprite": {
    "frame": { "x": 3300, "y": 0, "w": 100, "h": 100 },
    "rotated": false,
    "trimmed": false,
    "spriteSourceSize": { "x": 0, "y": 0, "w": 100, "h": 100 },
    "sourceSize": { "w": 100, "h": 100 },
    "duration": 100
   },
   "background-explosion-animated 34.aseprite": {
    "frame": { "x": 3400, "y": 0, "w": 100, "h": 100 },
    "rotated": false,
    "trimmed": false,
    "spriteSourceSize": { "x": 0, "y": 0, "w": 100, "h": 100 },
    "sourceSize": { "w": 100, "h": 100 },
    "duration": 100
   },
   "background-explosion-animated 35.aseprite": {
    "frame": { "x": 3500, "y": 0, "w": 100, "h": 100 },
    "rotated": false,
    "trimmed": false,
    "spriteSourceSize": { "x": 0, "y": 0, "w": 100, "h": 100 },
    "sourceSize": { "w": 100, "h": 100 },
    "duration": 100
   },
   "background-explosion-animated 36.aseprite": {
    "frame": { "x": 3600, "y": 0, "w": 100, "h": 100 },
    "rotated": false,
    "trimmed": false,
    "spriteSourceSize": { "x": 0, "y": 0, "w": 100, "h": 100 },
    "sourceSize": { "w": 100, "h": 100 },
    "duration": 100
   },
   "background-explosion-animated 37.aseprite": {
    "frame": { "x": 3700, "y": 0, "w": 100, "h": 100 },
    "rotated": false,
    "trimmed": false,
    "spriteSourceSize": { "x": 0, "y": 0, "w": 100, "h": 100 },
    "sourceSize": { "w": 100, "h": 100 },
    "duration": 100
   },
   "background-explosion-animated 38.aseprite": {
    "frame": { "x": 3800, "y": 0, "w": 100, "h": 100 },
    "rotated": false,
    "trimmed": false,
    "spriteSourceSize": { "x": 0, "y": 0, "w": 100, "h": 100 },
    "sourceSize": { "w": 100, "h": 100 },
    "duration": 100
   },
   "background-explosion-animated 39.aseprite": {
    "frame": { "x": 3900, "y": 0, "w": 100, "h": 100 },
    "rotated": false,
    "trimmed": false,
    "spriteSourceSize": { "x": 0, "y": 0, "w": 100, "h": 100 },
    "sourceSize": { "w": 100, "h": 100 },
    "duration": 100
   },
   "background-explosion-animated 40.aseprite": {
    "frame": { "x": 4000, "y": 0, "w": 100, "h": 100 },
    "rotated": false,
    "trimmed": false,
    "spriteSourceSize": { "x": 0, "y": 0, "w": 100, "h": 100 },
    "sourceSize": { "w": 100, "h": 100 },
    "duration": 100
   },
   "background-explosion-animated 41.aseprite": {
    "frame": { "x": 4100, "y": 0, "w": 100, "h": 100 },
    "rotated": false,
    "trimmed": false,
    "spriteSourceSize": { "x": 0, "y": 0, "w": 100, "h": 100 },
    "sourceSize": { "w": 100, "h": 100 },
    "duration": 100
   },
   "background-explosion-animated 42.aseprite": {
    "frame": { "x": 4200, "y": 0, "w": 100, "h": 100 },
    "rotated": false,
    "trimmed": false,
    "spriteSourceSize": { "x": 0, "y": 0, "w": 100, "h": 100 },
    "sourceSize": { "w": 100, "h": 100 },
    "duration": 100
   },
   "background-explosion-animated 43.aseprite": {
    "frame": { "x": 4300, "y": 0, "w": 100, "h": 100 },
    "rotated": false,
    "trimmed": false,
    "spriteSourceSize": { "x": 0, "y": 0, "w": 100, "h": 100 },
    "sourceSize": { "w": 100, "h": 100 },
    "duration": 100
   },
   "background-explosion-animated 44.aseprite": {
    "frame": { "x": 4400, "y": 0, "w": 100, "h": 100 },
    "rotated": false,
    "trimmed": false,
    "spriteSourceSize": { "x": 0, "y": 0, "w": 100, "h": 100 },
    "sourceSize": { "w": 100, "h": 100 },
    "duration": 100
   },
   "background-explosion-animated 45.aseprite": {
    "frame": { "x": 4500, "y": 0, "w": 100, "h": 100 },
    "rotated": false,
    "trimmed": false,
    "spriteSourceSize": { "x": 0, "y": 0, "w": 100, "h": 100 },
    "sourceSize": { "w": 100, "h": 100 },
    "duration": 100
   },
   "background-explosion-animated 46.aseprite": {
    "frame": { "x": 4600, "y": 0, "w": 100, "h": 100 },
    "rotated": false,
    "trimmed": false,
    "spriteSourceSize": { "x": 0, "y": 0, "w": 100, "h": 100 },
    "sourceSize": { "w": 100, "h": 100 },
    "duration": 100
   },
   "background-explosion-animated 47.aseprite": {
    "frame": { "x": 4700, "y": 0, "w": 100, "h": 100 },
    "rotated": false,
    "trimmed": false,
    "spriteSourceSize": { "x": 0, "y": 0, "w": 100, "h": 100 },
    "sourceSize": { "w": 100, "h": 100 },
    "duration": 100
   },
   "background-explosion-animated 48.aseprite": {
    "frame": { "x": 4800, "y": 0, "w": 100, "h": 100 },
    "rotated": false,
    "trimmed": false,
    "spriteSourceSize": { "x": 0, "y": 0, "w": 100, "h": 100 },
    "sourceSize": { "w": 100, "h": 100 },
    "duration": 100
   },
   "background-explosion-animated 49.aseprite": {
    "frame": { "x": 4900, "y": 0, "w": 100, "h": 100 },
    "rotated": false,
    "trimmed": false,
    "spriteSourceSize": { "x": 0, "y": 0, "w": 100, "h": 100 },
    "sourceSize": { "w": 100, "h": 100 },
    "duration": 100
   },
   "background-explosion-animated 50.aseprite": {
    "frame": { "x": 5000, "y": 0, "w": 100, "h": 100 },
    "rotated": false,
    "trimmed": false,
    "spriteSourceSize": { "x": 0, "y": 0, "w": 100, "h": 100 },
    "sourceSize": { "w": 100, "h": 100 },
    "duration": 100
   },
   "background-explosion-animated 51.aseprite": {
    "frame": { "x": 5100, "y": 0, "w": 100, "h": 100 },
    "rotated": false,
    "trimmed": false,
    "spriteSourceSize": { "x": 0, "y": 0, "w": 100, "h": 100 },
    "sourceSize": { "w": 100, "h": 100 },
    "duration": 100
   },
   "background-explosion-animated 52.aseprite": {
    "frame": { "x": 5200, "y": 0, "w": 100, "h": 100 },
    "rotated": false,
    "trimmed": false,
    "spriteSourceSize": { "x": 0, "y": 0, "w": 100, "h": 100 },
    "sourceSize": { "w": 100, "h": 100 },
    "duration": 100
   },
   "background-explosion-animated 53.aseprite": {
    "frame": { "x": 5300, "y": 0, "w": 100, "h": 100 },
    "rotated": false,
    "trimmed": false,
    "spriteSourceSize": { "x": 0, "y": 0, "w": 100, "h": 100 },
    "sourceSize": { "w": 100, "h": 100 },
    "duration": 100
   },
   "background-explosion-animated 54.aseprite": {
    "frame": { "x": 5400, "y": 0, "w": 100, "h": 100 },
    "rotated": false,
    "trimmed": false,
    "spriteSourceSize": { "x": 0, "y": 0, "w": 100, "h": 100 },
    "sourceSize": { "w": 100, "h": 100 },
    "duration": 100
   },
   "background-explosion-animated 55.aseprite": {
    "frame": { "x": 5500, "y": 0, "w": 100, "h": 100 },
    "rotated": false,
    "trimmed": false,
    "spriteSourceSize": { "x": 0, "y": 0, "w": 100, "h": 100 },
    "sourceSize": { "w": 100, "h": 100 },
    "duration": 100
   },
   "background-explosion-animated 56.aseprite": {
    "frame": { "x": 5600, "y": 0, "w": 100, "h": 100 },
    "rotated": false,
    "trimmed": false,
    "spriteSourceSize": { "x": 0, "y": 0, "w": 100, "h": 100 },
    "sourceSize": { "w": 100, "h": 100 },
    "duration": 100
   },
   "background-explosion-animated 57.aseprite": {
    "frame": { "x": 5700, "y": 0, "w": 100, "h": 100 },
    "rotated": false,
    "trimmed": false,
    "spriteSourceSize": { "x": 0, "y": 0, "w": 100, "h": 100 },
    "sourceSize": { "w": 100, "h": 100 },
    "duration": 100
   },
   "background-explosion-animated 58.aseprite": {
    "frame": { "x": 5800, "y": 0, "w": 100, "h": 100 },
    "rotated": false,
    "trimmed": false,
    "spriteSourceSize": { "x": 0, "y": 0, "w": 100, "h": 100 },
    "sourceSize": { "w": 100, "h": 100 },
    "duration": 100
   },
   "background-explosion-animated 59.aseprite": {
    "frame": { "x": 5900, "y": 0, "w": 100, "h": 100 },
    "rotated": false,
    "trimmed": false,
    "spriteSourceSize": { "x": 0, "y": 0, "w": 100, "h": 100 },
    "sourceSize": { "w": 100, "h": 100 },
    "duration": 100
   },
   "background-explosion-animated 60.aseprite": {
    "frame": { "x": 6000, "y": 0, "w": 100, "h": 100 },
    "rotated": false,
    "trimmed": false,
    "spriteSourceSize": { "x": 0, "y": 0, "w": 100, "h": 100 },
    "sourceSize": { "w": 100, "h": 100 },
    "duration": 100
   },
   "background-explosion-animated 61.aseprite": {
    "frame": { "x": 6100, "y": 0, "w": 100, "h": 100 },
    "rotated": false,
    "trimmed": false,
    "spriteSourceSize": { "x": 0, "y": 0, "w": 100, "h": 100 },
    "sourceSize": { "w": 100, "h": 100 },
    "duration": 100
   },
   "background-explosion-animated 62.aseprite": {
    "frame": { "x": 6200, "y": 0, "w": 100, "h": 100 },
    "rotated": false,
    "trimmed": false,
    "spriteSourceSize": { "x": 0, "y": 0, "w": 100, "h": 100 },
    "sourceSize": { "w": 100, "h": 100 },
    "duration": 100
   },
   "background-explosion-animated 63.aseprite": {
    "frame": { "x": 6300, "y": 0, "w": 100, "h": 100 },
    "rotated": false,
    "trimmed": false,
    "spriteSourceSize": { "x": 0, "y": 0, "w": 100, "h": 100 },
    "sourceSize": { "w": 100, "h": 100 },
    "duration": 100
   },
   "background-explosion-animated 64.aseprite": {
    "frame": { "x": 6400, "y": 0, "w": 100, "h": 100 },
    "rotated": false,
    "trimmed": false,
    "spriteSourceSize": { "x": 0, "y": 0, "w": 100, "h": 100 },
    "sourceSize": { "w": 100, "h": 100 },
    "duration": 100
   },
   "background-explosion-animated 65.aseprite": {
    "frame": { "x": 6500, "y": 0, "w": 100, "h": 100 },
    "rotated": false,
    "trimmed": false,
    "spriteSourceSize": { "x": 0, "y": 0, "w": 100, "h": 100 },
    "sourceSize": { "w": 100, "h": 100 },
    "duration": 100
   },
   "background-explosion-animated 66.aseprite": {
    "frame": { "x": 6600, "y": 0, "w": 100, "h": 100 },
    "rotated": false,
    "trimmed": false,
    "spriteSourceSize": { "x": 0, "y": 0, "w": 100, "h": 100 },
    "sourceSize": { "w": 100, "h": 100 },
    "duration": 100
   },
   "background-explosion-animated 67.aseprite": {
    "frame": { "x": 6700, "y": 0, "w": 100, "h": 100 },
    "rotated": false,
    "trimmed": false,
    "spriteSourceSize": { "x": 0, "y": 0, "w": 100, "h": 100 },
    "sourceSize": { "w": 100, "h": 100 },
    "duration": 100
   },
   "background-explosion-animated 68.aseprite": {
    "frame": { "x": 6800, "y": 0, "w": 100, "h": 100 },
    "rotated": false,
    "trimmed": false,
    "spriteSourceSize": { "x": 0, "y": 0, "w": 100, "h": 100 },
    "sourceSize": { "w": 100, "h": 100 },
    "duration": 100
   },
   "background-explosion-animated 69.aseprite": {
    "frame": { "x": 6900, "y": 0, "w": 100, "h": 100 },
    "rotated": false,
    "trimmed": false,
    "spriteSourceSize": { "x": 0, "y": 0, "w": 100, "h": 100 },
    "sourceSize": { "w": 100, "h": 100 },
    "duration": 100
   },
   "background-explosion-animated 70.aseprite": {
    "frame": { "x": 7000, "y": 0, "w": 100, "h": 100 },
    "rotated": false,
    "trimmed": false,
    "spriteSourceSize": { "x": 0, "y": 0, "w": 100, "h": 100 },
    "sourceSize": { "w": 100, "h": 100 },
    "duration": 100
   },
   "background-explosion-animated 71.aseprite": {
    "frame": { "x": 7100, "y": 0, "w": 100, "h": 100 },
    "rotated": false,
    "trimmed": false,
    "spriteSourceSize": { "x": 0, "y": 0, "w": 100, "h": 100 },
    "sourceSize": { "w": 100, "h": 100 },
    "duration": 100
   },
   "background-explosion-animated 72.aseprite": {
    "frame": { "x": 7200, "y": 0, "w": 100, "h": 100 },
    "rotated": false,
    "trimmed": false,
    "spriteSourceSize": { "x": 0, "y": 0, "w": 100, "h": 100 },
    "sourceSize": { "w": 100, "h": 100 },
    "duration": 100
   },
   "background-explosion-animated 73.aseprite": {
    "frame": { "x": 7300, "y": 0, "w": 100, "h": 100 },
    "rotated": false,
    "trimmed": false,
    "spriteSourceSize": { "x": 0, "y": 0, "w": 100, "h": 100 },
    "sourceSize": { "w": 100, "h": 100 },
    "duration": 100
   },
   "background-explosion-animated 74.aseprite": {
    "frame": { "x": 7400, "y": 0, "w": 100, "h": 100 },
    "rotated": false,
    "trimmed": false,
    "spriteSourceSize": { "x": 0, "y": 0, "w": 100, "h": 100 },
    "sourceSize": { "w": 100, "h": 100 },
    "duration": 100
   },
   "background-explosion-animated 75.aseprite": {
    "frame": { "x": 7500, "y": 0, "w": 100, "h": 100 },
    "rotated": false,
    "trimmed": false,
    "spriteSourceSize": { "x": 0, "y": 0, "w": 100, "h": 100 },
    "sourceSize": { "w": 100, "h": 100 },
    "duration": 100
   },
   "background-explosion-animated 76.aseprite": {
    "frame": { "x": 7600, "y": 0, "w": 100, "h": 100 },
    "rotated": false,
    "trimmed": false,
    "spriteSourceSize": { "x": 0, "y": 0, "w": 100, "h": 100 },
    "sourceSize": { "w": 100, "h": 100 },
    "duration": 100
   },
   "background-explosion-animated 77.aseprite": {
    "frame": { "x": 7700, "y": 0, "w": 100, "h": 100 },
    "rotated": false,
    "trimmed": false,
    "spriteSourceSize": { "x": 0, "y": 0, "w": 100, "h": 100 },
    "sourceSize": { "w": 100, "h": 100 },
    "duration": 100
   },
   "background-explosion-animated 78.aseprite": {
    "frame": { "x": 7800, "y": 0, "w": 100, "h": 100 },
    "rotated": false,
    "trimmed": false,
    "spriteSourceSize": { "x": 0, "y": 0, "w": 100, "h": 100 },
    "sourceSize": { "w": 100, "h": 100 },
    "duration": 100
   },
   "background-explosion-animated 79.aseprite": {
    "frame": { "x": 7900, "y": 0, "w": 100, "h": 100 },
    "rotated": false,
    "trimmed": false,
    "spriteSourceSize": { "x": 0, "y": 0, "w": 100, "h": 100 },
    "sourceSize": { "w": 100, "h": 100 },
    "duration": 100
   }
 },
 "meta": {
  "app": "http://www.aseprite.org/",
  "version": "1.2.25",
  "image": "background-explosion-animated.png",
  "format": "RGBA8888",
  "size": { "w": 8000, "h": 100 },
  "scale": "1",
  "frameTags": [
  ],
  "layers": [
   { "name": "Sprite Sheet", "opacity": 255, "blendMode": "normal" }
  ],
  "slices": [
  ]
 }
}
